FlaskSuper/FlaskSuper.py
FlaskSuper/__init__.py
FlaskSuper-0.0.1.dist-info/METADATA
FlaskSuper-0.0.1.dist-info/WHEEL
FlaskSuper-0.0.1.dist-info/top_level.txt
FlaskSuper-0.0.1.dist-info/RECORD
