Metadata-Version: 2.1
Name: FlaskSuper
Version: 0.0.1
Summary: A web framework built on top of Flask
Author: M.Abbas_Dev
Author-email: realmwls75@gmail.com
Platform: window
Platform: mac
Classifier: Programming Language :: Python :: 3
Requires-Dist: Flask
Requires-Dist: Flask-SQLAlchemy
